pypm/__init__.py
pypm/__main__.py
pypm/central_store.py
pypm/cli.py
pypm/environment_manager.py
pypm_manager-2.2.0.dist-info/licenses/LICENSE
pypm_manager-2.2.0.dist-info/METADATA
pypm_manager-2.2.0.dist-info/WHEEL
pypm_manager-2.2.0.dist-info/entry_points.txt
pypm_manager-2.2.0.dist-info/top_level.txt
pypm_manager-2.2.0.dist-info/RECORD
