Metadata-Version: 2.4
Name: pypm-manager
Version: 2.2.0
Summary: Python package manager with true multi-version support and Python version tagging - production ready
Home-page: https://github.com/Avishek8136/pypm
Author: Avishek
Author-email: Avishek <avishek8136@github.com>
License: MIT
Project-URL: Homepage, https://github.com/Avishek8136/pypm
Project-URL: Documentation, https://github.com/Avishek8136/pypm#readme
Project-URL: Repository, https://github.com/Avishek8136/pypm
Project-URL: Issues, https://github.com/Avishek8136/pypm/issues
Keywords: package-manager,environment,dependencies,storage,efficiency
Classifier: Development Status :: 4 - Beta
Classifier: Intended Audience :: Developers
Classifier: License :: OSI Approved :: MIT License
Classifier: Programming Language :: Python :: 3
Classifier: Programming Language :: Python :: 3.7
Classifier: Programming Language :: Python :: 3.8
Classifier: Programming Language :: Python :: 3.9
Classifier: Programming Language :: Python :: 3.10
Classifier: Programming Language :: Python :: 3.11
Classifier: Programming Language :: Python :: 3.12
Classifier: Operating System :: OS Independent
Classifier: Topic :: Software Development :: Libraries :: Python Modules
Classifier: Topic :: System :: Software Distribution
Requires-Python: >=3.7
License-File: LICENSE
Dynamic: author
Dynamic: home-page
Dynamic: license-file
Dynamic: requires-python
